deltakit_compile/__init__.py
deltakit_compile-0.6.2.dist-info/licenses/LICENSE
deltakit_compile-0.6.2.dist-info/METADATA
deltakit_compile-0.6.2.dist-info/WHEEL
deltakit_compile-0.6.2.dist-info/top_level.txt
deltakit_compile-0.6.2.dist-info/RECORD
