Metadata-Version: 2.4
Name: deltakit-compile
Version: 0.6.2
Summary: Deltakit (component deltakit-compile)
Author-email: Deltakit Team <deltakit@riverlane.com>
License-Expression: Apache-2.0
Project-URL: Homepage, https://github.com/Deltakit/deltakit
Project-URL: Bug Tracker, https://github.com/Deltakit/deltakit/issues
Project-URL: Changelog, https://github.com/Deltakit/deltakit/releases
Classifier: Development Status :: 1 - Planning
Classifier: Intended Audience :: Science/Research
Classifier: Intended Audience :: Developers
Classifier: Operating System :: OS Independent
Classifier: Programming Language :: Python
Classifier: Programming Language :: Python :: 3
Classifier: Programming Language :: Python :: 3 :: Only
Classifier: Programming Language :: Python :: 3.10
Classifier: Programming Language :: Python :: 3.11
Classifier: Programming Language :: Python :: 3.12
Classifier: Programming Language :: Python :: 3.13
Classifier: Topic :: Scientific/Engineering :: Quantum Computing
Classifier: Typing :: Typed
Requires-Python: >=3.10
License-File: LICENSE
Dynamic: license-file
